migoapiclient/__init__.py
migoapiclient/api_client.py
migoapiclient/file_manager.py
src/__init__.py
migoapiclient-1.2.4.dist-info/METADATA
migoapiclient-1.2.4.dist-info/WHEEL
migoapiclient-1.2.4.dist-info/top_level.txt
migoapiclient-1.2.4.dist-info/RECORD
