Metadata-Version: 2.1
Name: migoapiclient
Version: 1.2.4
Summary: 米果请求API客户端
Home-page: https://github.com/me/myproject
Author: pykira
Author-email: 2920167524@qq.com
License: MIT
Classifier: License :: OSI Approved :: MIT License
Classifier: Programming Language :: Python
Classifier: Programming Language :: Python :: 3
Classifier: Programming Language :: Python :: 3.6
Classifier: Programming Language :: Python :: Implementation :: CPython
Classifier: Programming Language :: Python :: Implementation :: PyPy
Requires-Python: >=3.5.0
